{
  "hash": "bff36074",
  "configHash": "3c841e99",
  "lockfileHash": "270f18da",
  "browserHash": "cad1102a",
  "optimized": {
    "react-dom/client": {
      "src": "../../node_modules/react-dom/client.js",
      "file": "react-dom_client.js",
      "fileHash": "05c95961",
      "needsInterop": true
    },
    "react": {
      "src": "../../node_modules/react/index.js",
      "file": "react.js",
      "fileHash": "39fb77de",
      "needsInterop": true
    },
    "react/jsx-dev-runtime": {
      "src": "../../node_modules/react/jsx-dev-runtime.js",
      "file": "react_jsx-dev-runtime.js",
      "fileHash": "4ce161f2",
      "needsInterop": true
    }
  },
  "chunks": {
    "react-FLDBkK74": {
      "file": "react-FLDBkK74.js",
      "isDynamicEntry": false
    }
  }
}